{
  "segments": {
    "proactive_parent": {
      "discovered_characteristics": {
        "engagement_level": "high",
        "exploration_level": "high",
        "conversion_potential": "medium",
        "device_affinity": "mobile",
        "active_time": 23,
        "sample_size": 10
      },
      "behavioral_metrics": {
        "avg_session_duration": 324.6,
        "avg_pages_per_session": 6.7,
        "conversion_rate": 0.04560619519879116
      }
    },
    "researching_parent": {
      "discovered_characteristics": {
        "engagement_level": "high",
        "exploration_level": "high",
        "conversion_potential": "medium",
        "device_affinity": "desktop",
        "active_time": 9,
        "sample_size": 12
      },
      "behavioral_metrics": {
        "avg_session_duration": 394.0,
        "avg_pages_per_session": 5.25,
        "conversion_rate": 0.04389730039685678
      }
    },
    "concerned_parent": {
      "discovered_characteristics": {
        "engagement_level": "medium",
        "exploration_level": "high",
        "conversion_potential": "medium",
        "device_affinity": "mobile",
        "active_time": 6,
        "sample_size": 7
      },
      "behavioral_metrics": {
        "avg_session_duration": 289.85714285714283,
        "avg_pages_per_session": 5.285714285714286,
        "conversion_rate": 0.04529601534387601
      }
    },
    "crisis_parent": {
      "discovered_characteristics": {
        "engagement_level": "high",
        "exploration_level": "medium",
        "conversion_potential": "medium",
        "device_affinity": "desktop",
        "active_time": 13,
        "sample_size": 15
      },
      "behavioral_metrics": {
        "avg_session_duration": 393.26666666666665,
        "avg_pages_per_session": 4.2,
        "conversion_rate": 0.045999841538498815
      }
    }
  },
  "channels": {
    "google": {
      "views": 50000,
      "sessions": 40000,
      "conversions": 800
    },
    "facebook": {
      "views": 30000,
      "sessions": 25000,
      "conversions": 375
    },
    "organic": {
      "views": 104363,
      "sessions": 81348,
      "conversions": 0,
      "pages": [
        "/screen-time",
        "/parental-controls",
        "/screen-time",
        "/balance-app",
        "/balance-app",
        "/family-safety",
        "/parental-controls",
        "/usage-reports",
        "/family-safety",
        "/usage-reports",
        "/parental-controls",
        "/usage-reports",
        "/family-safety",
        "/screen-time",
        "/parental-controls",
        "/balance-app",
        "/family-safety",
        "/usage-reports",
        "/usage-reports",
        "/usage-reports",
        "/family-safety",
        "/screen-time",
        "/balance-app",
        "/balance-app",
        "/usage-reports",
        "/balance-app",
        "/screen-time",
        "/parental-controls",
        "/parental-controls",
        "/usage-reports",
        "/parental-controls",
        "/parental-controls",
        "/parental-controls",
        "/family-safety",
        "/family-safety",
        "/parental-controls",
        "/usage-reports",
        "/usage-reports",
        "/balance-app",
        "/screen-time",
        "/balance-app",
        "/usage-reports",
        "/usage-reports",
        "/balance-app",
        "/usage-reports",
        "/parental-controls",
        "/usage-reports",
        "/usage-reports",
        "/parental-controls",
        "/balance-app",
        "/balance-app",
        "/balance-app",
        "/family-safety",
        "/family-safety",
        "/usage-reports",
        "/family-safety",
        "/usage-reports",
        "/family-safety",
        "/screen-time",
        "/usage-reports",
        "/usage-reports",
        "/parental-controls",
        "/screen-time",
        "/parental-controls",
        "/screen-time",
        "/family-safety",
        "/balance-app",
        "/usage-reports",
        "/parental-controls",
        "/family-safety",
        "/parental-controls",
        "/balance-app",
        "/parental-controls",
        "/parental-controls",
        "/usage-reports",
        "/balance-app",
        "/screen-time",
        "/screen-time",
        "/balance-app",
        "/balance-app",
        "/family-safety",
        "/usage-reports",
        "/screen-time",
        "/balance-app",
        "/parental-controls",
        "/balance-app",
        "/usage-reports",
        "/usage-reports",
        "/usage-reports",
        "/balance-app",
        "/balance-app",
        "/parental-controls",
        "/balance-app",
        "/family-safety",
        "/family-safety",
        "/parental-controls"
      ]
    }
  },
  "devices": {
    "tablet": {
      "views": 40255,
      "sessions": 31354,
      "users": 0,
      "pages": [
        "/screen-time",
        "/family-safety",
        "/usage-reports",
        "/family-safety",
        "/screen-time",
        "/usage-reports",
        "/balance-app",
        "/balance-app",
        "/screen-time",
        "/parental-controls",
        "/usage-reports",
        "/parental-controls",
        "/family-safety",
        "/balance-app",
        "/screen-time",
        "/usage-reports",
        "/usage-reports",
        "/balance-app",
        "/usage-reports",
        "/parental-controls",
        "/parental-controls",
        "/family-safety",
        "/screen-time",
        "/family-safety",
        "/usage-reports",
        "/parental-controls",
        "/family-safety",
        "/balance-app",
        "/screen-time",
        "/family-safety",
        "/screen-time",
        "/balance-app",
        "/balance-app",
        "/usage-reports",
        "/usage-reports",
        "/parental-controls"
      ]
    },
    "mobile": {
      "views": 32837,
      "sessions": 29127,
      "users": 0,
      "pages": [
        "/parental-controls",
        "/balance-app",
        "/parental-controls",
        "/usage-reports",
        "/screen-time",
        "/usage-reports",
        "/parental-controls",
        "/parental-controls",
        "/family-safety",
        "/usage-reports",
        "/usage-reports",
        "/usage-reports",
        "/balance-app",
        "/balance-app",
        "/family-safety",
        "/usage-reports",
        "/usage-reports",
        "/family-safety",
        "/usage-reports",
        "/parental-controls",
        "/screen-time",
        "/screen-time",
        "/parental-controls",
        "/usage-reports",
        "/balance-app",
        "/parental-controls",
        "/usage-reports",
        "/balance-app",
        "/balance-app",
        "/parental-controls",
        "/balance-app",
        "/family-safety"
      ]
    },
    "desktop": {
      "views": 31271,
      "sessions": 20867,
      "users": 0,
      "pages": [
        "/screen-time",
        "/balance-app",
        "/parental-controls",
        "/usage-reports",
        "/family-safety",
        "/usage-reports",
        "/parental-controls",
        "/balance-app",
        "/family-safety",
        "/usage-reports",
        "/family-safety",
        "/balance-app",
        "/parental-controls",
        "/parental-controls",
        "/usage-reports",
        "/balance-app",
        "/balance-app",
        "/family-safety",
        "/usage-reports",
        "/parental-controls",
        "/balance-app",
        "/parental-controls",
        "/balance-app",
        "/parental-controls",
        "/screen-time",
        "/balance-app",
        "/usage-reports",
        "/family-safety"
      ]
    }
  },
  "temporal": {
    "discovered_peak_hours": [
      23,
      13,
      9,
      1,
      16
    ],
    "peak_hour_activity": {
      "23": 5,
      "13": 4,
      "9": 4,
      "1": 3,
      "16": 3
    },
    "avg_session_duration": 361.40909090909093,
    "total_sessions_analyzed": 44
  },
  "last_updated": "2025-08-29T03:18:10.918753"
}